hexLang/__init__.py
hexLang/__main__.py
hexLang/__rajiniworld__.py
hexLang/ast/__init__.py
hexLang/ast/base.py
hexLang/ast/blocks.py
hexLang/ast/control.py
hexLang/ast/ops.py
hexLang/exceptions.py
hexLang/lexer.py
hexLang/parser/__init__.py
hexLang/parser/atom_parser.py
hexLang/parser/expr_parser.py
hexLang/parser/flow_parser.py
hexLang/parser/func_parser.py
hexLang/parser/ops_parser.py
hexLang/parser/parser.py
hexLang/parser/print_parser.py
hexLang/parser/stmt_parser.py
hexLang/parser/var_parser.py
hexLang/runner.py
hexLang/token.yml
hexLang/utils.py
hexlang-0.3.2.dist-info/entry_points.txt
hexlang-0.3.2.dist-info/LICENSE
hexlang-0.3.2.dist-info/METADATA
hexlang-0.3.2.dist-info/WHEEL
hexlang-0.3.2.dist-info/RECORD
